README.txt
setup.cfg
setup.py
logionmath2d/Graphs2DOperation.py
logionmath2d/Math2DOperation.py
logionmath2d/__init__.py
logionmath2d.egg-info/PKG-INFO
logionmath2d.egg-info/SOURCES.txt
logionmath2d.egg-info/dependency_links.txt
logionmath2d.egg-info/top_level.txt