Metadata-Version: 1.1
Name: logionmath2d
Version: 0.1
Summary: Lib for math operations
Home-page: https://github.com/pythonDev2060/logionmath2d
Author: PYTHON DEV
Author-email: pythonDev.2030@gmail.com
License: MIT
Download-URL: https://github.com/pythonDev2060/logionmath2d/archive/v_04.tar.gz
Keywords: GRAPHS,MATHS,WORDS
Platform: UNKNOWN
Classifier: Development Status :: 3 - Alpha
Classifier: Intended Audience :: Developers
Classifier: Topic :: Software Development :: Build Tools
Classifier: License :: OSI Approved :: MIT License
Classifier: Programming Language :: Python :: 3
Classifier: Programming Language :: Python :: 3.4
Classifier: Programming Language :: Python :: 3.5
Classifier: Programming Language :: Python :: 3.6
Classifier: Programming Language :: Python :: 3.7
